torlog/__init__.py
torlog/setup.py
torlog/torlogger.py
torlog/utils/__init__.py
torlog/utils/errors.py
torlog/utils/logic.py
TorLog-0.0.8.dist-info/METADATA
TorLog-0.0.8.dist-info/WHEEL
TorLog-0.0.8.dist-info/top_level.txt
TorLog-0.0.8.dist-info/RECORD
