Metadata-Version: 2.1
Name: TorLog
Version: 0.0.8
Summary: Simple logging tool for Python | tore.ofc on discord.
Home-page: https://github.com/Tore09/torlog
Author: tore.ofc
